osu_tools/__init__.py
osu_tools/calculator.py
osu_tools/lib/.gitkeep
osu_tools/lib/Alba.CsConsoleFormat.dll
osu_tools/lib/AutoMapper.dll
osu_tools/lib/Commons.Music.Midi.dll
osu_tools/lib/DiffPlex.dll
osu_tools/lib/FFmpeg.AutoGen.dll
osu_tools/lib/HidSharpCore.dll
osu_tools/lib/HtmlAgilityPack.dll
osu_tools/lib/Humanizer.dll
osu_tools/lib/JetBrains.Annotations.dll
osu_tools/lib/Markdig.dll
osu_tools/lib/McMaster.Extensions.CommandLineUtils.dll
osu_tools/lib/MessagePack.Annotations.dll
osu_tools/lib/MessagePack.dll
osu_tools/lib/Microsoft.AspNetCore.Connections.Abstractions.dll
osu_tools/lib/Microsoft.AspNetCore.Http.Connections.Client.dll
osu_tools/lib/Microsoft.AspNetCore.Http.Connections.Common.dll
osu_tools/lib/Microsoft.AspNetCore.SignalR.Client.Core.dll
osu_tools/lib/Microsoft.AspNetCore.SignalR.Client.dll
osu_tools/lib/Microsoft.AspNetCore.SignalR.Common.dll
osu_tools/lib/Microsoft.AspNetCore.SignalR.Protocols.Json.dll
osu_tools/lib/Microsoft.AspNetCore.SignalR.Protocols.MessagePack.dll
osu_tools/lib/Microsoft.AspNetCore.SignalR.Protocols.NewtonsoftJson.dll
osu_tools/lib/Microsoft.Bcl.AsyncInterfaces.dll
osu_tools/lib/Microsoft.Bcl.TimeProvider.dll
osu_tools/lib/Microsoft.Data.Sqlite.dll
osu_tools/lib/Microsoft.Diagnostics.NETCore.Client.dll
osu_tools/lib/Microsoft.Diagnostics.Runtime.dll
osu_tools/lib/Microsoft.Extensions.Configuration.Abstractions.dll
osu_tools/lib/Microsoft.Extensions.DependencyInjection.Abstractions.dll
osu_tools/lib/Microsoft.Extensions.DependencyInjection.dll
osu_tools/lib/Microsoft.Extensions.Features.dll
osu_tools/lib/Microsoft.Extensions.Logging.Abstractions.dll
osu_tools/lib/Microsoft.Extensions.Logging.dll
osu_tools/lib/Microsoft.Extensions.ObjectPool.dll
osu_tools/lib/Microsoft.Extensions.Options.dll
osu_tools/lib/Microsoft.Extensions.Primitives.dll
osu_tools/lib/Microsoft.NET.StringTools.dll
osu_tools/lib/Microsoft.Toolkit.HighPerformance.dll
osu_tools/lib/MongoDB.Bson.dll
osu_tools/lib/Newtonsoft.Json.dll
osu_tools_py-0.1.2.dist-info/METADATA
osu_tools_py-0.1.2.dist-info/WHEEL
osu_tools_py-0.1.2.dist-info/licenses/LICENSE
osu_tools_py-0.1.2.dist-info/RECORD
