Metadata-Version: 2.4
Name: osu-tools-py
Version: 0.1.2
Summary: A Python wrapper for osu! tools using pythonnet
License-File: LICENSE
Requires-Python: <3.14,>=3.10
Requires-Dist: pythonnet>=3.0.5
